pyplanets/__init__.py
pyplanets/sun.py
pyplanets/core/__init__.py
pyplanets/core/angle.py
pyplanets/core/base.py
pyplanets/core/constellation.py
pyplanets/core/coordinates.py
pyplanets/core/curvefitting.py
pyplanets/core/ellipsoid.py
pyplanets/core/epoch.py
pyplanets/core/interpolation.py
pyplanets/parameters/__init__.py
pyplanets/parameters/coordinates_params.py
pyplanets/parameters/earth_params.py
pyplanets/parameters/jupiter_params.py
pyplanets/parameters/mars_params.py
pyplanets/parameters/mercury_params.py
pyplanets/parameters/neptune_params.py
pyplanets/parameters/pluto_params.py
pyplanets/parameters/saturn_params.py
pyplanets/parameters/uranus_params.py
pyplanets/parameters/venus_params.py
pyplanets/planets/__init__.py
pyplanets/planets/earth.py
pyplanets/planets/jupiter.py
pyplanets/planets/mars.py
pyplanets/planets/mercury.py
pyplanets/planets/minor.py
pyplanets/planets/neptune.py
pyplanets/planets/planet.py
pyplanets/planets/pluto.py
pyplanets/planets/saturn.py
pyplanets/planets/uranus.py
pyplanets/planets/venus.py
pyplanets-0.4.2.dist-info/COPYING.LESSER
pyplanets-0.4.2.dist-info/LICENSE.txt
pyplanets-0.4.2.dist-info/METADATA
pyplanets-0.4.2.dist-info/WHEEL
pyplanets-0.4.2.dist-info/top_level.txt
pyplanets-0.4.2.dist-info/RECORD
