Metadata-Version: 2.1
Name: pyplanets
Version: 0.4.2
Summary: PyPlanets: Object-oriented refactoring of PyMeeus, a Python library implementing astronomical algorithms.
Home-page: https://github.com/martin5f/pyplanets
Author: Martin Fünffinger
Author-email: martinfl633@gmail.com
License: LGPLv3
Download-URL: https://github.com/martin5f/pyplanets
Keywords: astronomy planets ephemeris Meeus VSOP87 module library
Platform: UNKNOWN
Classifier: Development Status :: 4 - Beta
Classifier: Environment :: Console
Classifier: Intended Audience :: Developers
Classifier: Intended Audience :: Education
Classifier: Intended Audience :: Science/Research
Classifier: License :: OSI Approved :: GNU Lesser General Public License v3 (LGPLv3)
Classifier: Operating System :: OS Independent
Classifier: Programming Language :: Python :: 3
Classifier: Topic :: Scientific/Engineering :: Astronomy
